dbus_trace.py
dbus_trace-0.1.dist-info/entry_points.txt
dbus_trace-0.1.dist-info/LICENSE
dbus_trace-0.1.dist-info/WHEEL
dbus_trace-0.1.dist-info/METADATA
dbus_trace-0.1.dist-info/RECORD
