Metadata-Version: 2.1
Name: dbus_trace
Version: 0.1
Summary: Inspect the D-Bus messages a program sends and receives
Author-email: Thomas Kluyver <thomas@kluyver.me.uk>
Requires-Python: >= 3.8
Classifier: License :: OSI Approved :: MIT License
Requires-Dist: trio
Requires-Dist: jeepney >= 0.7
Project-URL: Home, https://gitlab.com/takluyver/dbus-trace
